setup.py
auto_visualizations/Barchartvisualization.py
auto_visualizations/Bubblechartvisualization.py
auto_visualizations/Execution_code.py
auto_visualizations/Generalvisualization.py
auto_visualizations/Histogramvisualization.py
auto_visualizations/Piechartvisualization.py
auto_visualizations/__init__.py
auto_visualizations.egg-info/PKG-INFO
auto_visualizations.egg-info/SOURCES.txt
auto_visualizations.egg-info/dependency_links.txt
auto_visualizations.egg-info/not-zip-safe
auto_visualizations.egg-info/top_level.txt