Metadata-Version: 1.0
Name: auto-visualizations
Version: 0.3
Summary: Data Visualization
Home-page: UNKNOWN
Author: UNKNOWN
Author-email: UNKNOWN
License: UNKNOWN
Platform: UNKNOWN
